{
    "Routes": [
      {
        "id": 1,
        "destination": "Nairobi - Kisumu",
        "time": "10:30 PM",
        "company":"GREENLINE SAFARIS",
        "seats":45,
        "price":"KSH 2500" 
      },
      {
        "id": 2,
        "destination": "Nairobi - Kitale",
        "time": "8:00 AM",
        "company": "EASYCOACH",
        "seats":30,
        "price": "KSH 1400"
      },
      {
        "id": 3,
        "destination":"Nairobi - Mombasa",
        "time":"9:30 PM",
        "company":"MODERN-COAST",
        "seats":40,
        "price":"KSH 3000"
      },
      {
        "id":4,
        "destination":"Nairobi - Kisumu",
        "time":"9:30 PM",
        "company":"EASYCOACH",
        "seats":35,
        "price":"KSH 2500"
      }
    ]
  }